MANIFEST.in
README.rst
setup.py
toasyncio/__init__.py
toasyncio/gen.py
toasyncio/testing.py
toasyncio.egg-info/PKG-INFO
toasyncio.egg-info/SOURCES.txt
toasyncio.egg-info/dependency_links.txt
toasyncio.egg-info/not-zip-safe
toasyncio.egg-info/requires.txt
toasyncio.egg-info/top_level.txt