Metadata-Version: 1.1
Name: toasyncio
Version: 0.5.3
Summary: Transparent convert any asyncio futures and inline yield methods to tornado futures.
Home-page: https://github.com/mosquito/toasyncio
Author: Ilya Smirnov <ilya94@mail.ru>, Dmitry Orlov <me@mosquito.su>
Author-email: ilya94@mail.ru, me@mosquito.su
License: MIT
Keywords: tornado,asyncio
Platform: UNKNOWN
Classifier: Environment :: Console
Classifier: Programming Language :: Python :: 3 :: Only
Classifier: Programming Language :: Python :: 3.4
Classifier: Programming Language :: Python :: 3.5
